tdl_xoa_driver-1.7.2.dist-info/licenses/LICENSE
xoa_driver/__init__.py
xoa_driver/enums.py
xoa_driver/exceptions.py
xoa_driver/hlfuncs.py
xoa_driver/lli.py
xoa_driver/misc.py
xoa_driver/modules.py
xoa_driver/ports.py
xoa_driver/testers.py
xoa_driver/utils.py
xoa_driver/functions/__init__.py
xoa_driver/functions/anlt.py
xoa_driver/functions/anlt_ll_debug.py
xoa_driver/functions/async_wrapper.py
xoa_driver/functions/exceptions.py
xoa_driver/functions/headers.py
xoa_driver/functions/layer1_adv.py
xoa_driver/functions/mgmt.py
xoa_driver/functions/tools.py
xoa_driver/functions/xcvr.py
xoa_driver/functions/cli/__init__.py
xoa_driver/functions/cli/_cli_manager.py
xoa_driver/functions/cli/_config_block.py
xoa_driver/functions/cli/_socket_driver.py
xoa_driver/functions/cli/port_config.py
xoa_driver/functions/cli/testbed_config.py
xoa_driver/functions/cmis/__init__.py
xoa_driver/functions/cmis/_constants.py
xoa_driver/functions/cmis/_replies.py
xoa_driver/functions/cmis/_utils.py
xoa_driver/functions/cmis/cdb.py
xoa_driver/internals/__init__.py
xoa_driver/internals/warn.py
xoa_driver/internals/commands/__init__.py
xoa_driver/internals/commands/c_commands.py
xoa_driver/internals/commands/enums.py
xoa_driver/internals/commands/m4_commands.py
xoa_driver/internals/commands/m4e_commands.py
xoa_driver/internals/commands/m_commands.py
xoa_driver/internals/commands/p4_commands.py
xoa_driver/internals/commands/p4e_commands.py
xoa_driver/internals/commands/p4g_commands.py
xoa_driver/internals/commands/p_commands.py
xoa_driver/internals/commands/pc_commands.py
xoa_driver/internals/commands/pd_commands.py
xoa_driver/internals/commands/pe_commands.py
xoa_driver/internals/commands/pec_commands.py
xoa_driver/internals/commands/ped_commands.py
xoa_driver/internals/commands/pef_commands.py
xoa_driver/internals/commands/pf_commands.py
xoa_driver/internals/commands/pl1_commands.py
xoa_driver/internals/commands/pl1ad_commands.py
xoa_driver/internals/commands/pl_commands.py
xoa_driver/internals/commands/pm_commands.py
tdl_xoa_driver-1.7.2.dist-info/METADATA
tdl_xoa_driver-1.7.2.dist-info/WHEEL
tdl_xoa_driver-1.7.2.dist-info/top_level.txt
tdl_xoa_driver-1.7.2.dist-info/RECORD
