Metadata-Version: 2.4
Name: tdl-xoa-driver
Version: 1.7.2
Summary: TDL XOA Python API is a Python library providing user-friendly communication interfaces to Teledyne LeCroy Xena Ethernet traffic generation test equipment. It provides a rich collection of APIs that can be used to either write test scripts or develop applications.
Home-page: https://github.com/xenanetworks/tdl-xoa-driver
Author: Leonard Yu, Zoltan Hanisch
Author-email: Leonard.Yu@teledyne.com, Zoltan.Hanisch@teledyne.com
Maintainer: Teledyne LeCroy
Maintainer-email: xena-sales@teledyne.com
License: Apache 2.0
Classifier: Development Status :: 5 - Production/Stable
Classifier: Intended Audience :: Developers
Classifier: Topic :: Software Development :: Libraries :: Python Modules
Classifier: License :: OSI Approved :: Apache Software License
Classifier: Programming Language :: Python :: 3.11
Classifier: Programming Language :: Python :: 3.12
Classifier: Programming Language :: Python :: 3.13
Classifier: Programming Language :: Python :: 3.14
Requires-Python: >=3.11
License-File: LICENSE
Dynamic: author
Dynamic: author-email
Dynamic: classifier
Dynamic: description
Dynamic: description-content-type
Dynamic: home-page
Dynamic: license
Dynamic: license-file
Dynamic: maintainer
Dynamic: maintainer-email
Dynamic: requires-python
Dynamic: summary
